Metadata-Version: 2.1
Name: pydeobf
Version: 0.1
Summary: Python-based installation package. DLL/API Support
